odoo/addons/fieldservice_account/README.rst
odoo/addons/fieldservice_account/__init__.py
odoo/addons/fieldservice_account/__manifest__.py
odoo/addons/fieldservice_account/data/time_products.xml
odoo/addons/fieldservice_account/models/__init__.py
odoo/addons/fieldservice_account/models/account_invoice.py
odoo/addons/fieldservice_account/models/analytic_account.py
odoo/addons/fieldservice_account/models/fsm_location.py
odoo/addons/fieldservice_account/models/fsm_order.py
odoo/addons/fieldservice_account/readme/CONFIGURE.rst
odoo/addons/fieldservice_account/readme/CONTRIBUTORS.rst
odoo/addons/fieldservice_account/readme/CREDITS.rst
odoo/addons/fieldservice_account/readme/DESCRIPTION.rst
odoo/addons/fieldservice_account/readme/INSTALL.rst
odoo/addons/fieldservice_account/readme/USAGE.rst
odoo/addons/fieldservice_account/static/description/icon.png
odoo/addons/fieldservice_account/static/description/index.html
odoo/addons/fieldservice_account/views/account.xml
odoo/addons/fieldservice_account/views/account_invoice_view.xml
odoo/addons/fieldservice_account/views/fsm_location.xml
odoo/addons/fieldservice_account/views/fsm_order.xml
odoo11_addon_fieldservice_account-11.0.0.2.0.dist-info/METADATA
odoo11_addon_fieldservice_account-11.0.0.2.0.dist-info/RECORD
odoo11_addon_fieldservice_account-11.0.0.2.0.dist-info/WHEEL
odoo11_addon_fieldservice_account-11.0.0.2.0.dist-info/top_level.txt
